odoo/addons/stock_location_fill_state_qty_picked/README.rst
odoo/addons/stock_location_fill_state_qty_picked/__init__.py
odoo/addons/stock_location_fill_state_qty_picked/__manifest__.py
odoo/addons/stock_location_fill_state_qty_picked/i18n/it.po
odoo/addons/stock_location_fill_state_qty_picked/i18n/stock_location_fill_state_qty_picked.pot
odoo/addons/stock_location_fill_state_qty_picked/models/__init__.py
odoo/addons/stock_location_fill_state_qty_picked/models/stock_location.py
odoo/addons/stock_location_fill_state_qty_picked/readme/CONTRIBUTORS.md
odoo/addons/stock_location_fill_state_qty_picked/readme/DESCRIPTION.md
odoo/addons/stock_location_fill_state_qty_picked/static/description/icon.png
odoo/addons/stock_location_fill_state_qty_picked/static/description/index.html
odoo/addons/stock_location_fill_state_qty_picked/tests/__init__.py
odoo/addons/stock_location_fill_state_qty_picked/tests/test_location_fill_state.py
odoo_addon_stock_location_fill_state_qty_picked-18.0.1.0.0.4.dist-info/METADATA
odoo_addon_stock_location_fill_state_qty_picked-18.0.1.0.0.4.dist-info/WHEEL
odoo_addon_stock_location_fill_state_qty_picked-18.0.1.0.0.4.dist-info/top_level.txt
odoo_addon_stock_location_fill_state_qty_picked-18.0.1.0.0.4.dist-info/RECORD
