Metadata-Version: 2.1
Name: odoo-addon-stock_location_fill_state_qty_picked
Version: 18.0.1.0.0.4
Requires-Python: >=3.10
Requires-Dist: odoo-addon-stock_location_fill_state==18.0.*
Requires-Dist: odoo-addon-stock_move_line_qty_picked==18.0.*
Requires-Dist: odoo==18.0.*
Summary: Glue module between stock_location_fill_state and stock_move_line_qty_picked
Home-page: https://github.com/OCA/stock-logistics-warehouse
License: AGPL-3
Author: BCIM, ACSONE SA/NV, Odoo Community Association (OCA)
Author-email: support@odoo-community.org
Classifier: Programming Language :: Python
Classifier: Framework :: Odoo
Classifier: Framework :: Odoo :: 18.0
Classifier: License :: OSI Approved :: GNU Affero General Public License v3
